test.v
module test (
    input a,
    input b,
    input c,
    input d,
    input e,

    output s1,
    output s2,
    output s3,
    output s4,
    output s5,
    output s6,
    output s7
);

assign s1 = (a&c&(~d)&(~e)) |(a&b&(~c)&(~e)) | ((~a) &(~b)&d&e) | ((~a)&b&c&(~d)) | ((~a)&b&d&(~e)) | ((~b)&c&(~e)&d) | ((~b)&c&(~d)&e) | ((~a)&b&e&(~c)) | (a&(~b)&(~c)&d) | (a&(~c)&(~d)&e) |((~a)&(~b)&(~c)&(~d)&(~e)) |(a&b&c&d&e);


assign s2 = (e | d | c | b | a);

assign s3 = ((~a)&(~b)&(~c)) | ((~a)&(~b)&(~d)) | ((~a)&(~c)&(~d)) | ((~b)&(~c)&(~d)) | ((~a)&(~b)&(~e)) | ((~a)&(~c)&(~e)) | ((~b)&(~c)&(~e)) | ((~a)&(~d)&(~e)) | ((~b)&(~d)&(~e)) | ((~c)&(~d)&(~e)) | (b&c&d&e) | (a&c&d&e) | (a&b&d&e) | (a&b&c&e) | (a&b&c&d);


assign s4 = ((~a)&(~c)&d&e) | ((~a)&(~b)&c&d) | (a&(~b)&(~c)&d) | ((~a)&b&d&(~e)) | (a&b&(~c)&(~e)) | ((~a)&c&(~d)&e) | (a&(~b)&(~d)&e) | (b&(~d)&c&(~e)) | (a&(~b)&c&(~e)) | (b&(~c)&e&(~d)) | ((~a)& (~b)& (~c)& (~d)& (~e)) + (a&b&c&d&e);

assign s5 = ((~a)&(~b)&c&d&e) | ((~a)&b&(~c)&d&e) |((~a)&b&c&(~d)&e) |((~a)&b&c&d&(~e)) | (a&(~b)&(~c)&d&e) |(a&(~b)&c&(~d)&e) | (a&(~b)&c&d&(~e)) | (a&b&(~c)&e&(~d)) |(a&b&(~c)&d&(~e)) |(a&b&c&(~d)&(~e)) | (a&b&c&d&e);


assign s6 = ((~a)&(~b)&(~c)&(~d)) | ((~a)&(~b)&(~c)&(~e)) | ((~a)&(~b)&(~d)&(~e)) | ((~a)&(~c)&(~d)&(~e)) | ((~c)&(~b)&(~d)&(~e)) | (a&b&c&d&e);

assign s7 = ((~a)&(~b)) | ((~a)&(~c)) | ((~b)&(~c)) | ((~a)&(~d)) | ((~b)&(~d)) | ((~c)&(~d)) |((~a)&(~e)) |((~b)&(~e)) | ((~c)&(~e)) | ((~d)&(~e));

    
endmodule

testbench.v
`include "test.v"

module testbench ();


reg A;
reg B;
reg C;
reg D;
reg E;

wire S1;
wire S2;
wire S3;
wire S4;
wire S5;
wire S6;
wire S7;

test meuModuloTeste (A, B, C, D, E, S1, S2, S3, S4, S5, S6, S7);

initial begin
    $dumpfile ("testbench.vcd");
    $dumpvars (0, meuModuloTeste);
    
    $monitor("%b%b%b%b%b Saida = %b%b%b%b%b%b%b",A,B,C,D,E,S1,S2, S3, S4, S5, S6, S7);
            
        A = 1'b0; B = 1'b0; C = 1'b0; D = 1'b0; E = 1'b0; 
    #2; A = 1'b0; B = 1'b0; C = 1'b0; D = 1'b0; E = 1'b1;
    #2; A = 1'b0; B = 1'b0; C = 1'b0; D = 1'b1; E = 1'b0; 
    #2; A = 1'b0; B = 1'b0; C = 1'b0; D = 1'b1; E = 1'b1;
    #2; A = 1'b0; B = 1'b0; C = 1'b1; D = 1'b0; E = 1'b0; 
    #2; A = 1'b0; B = 1'b0; C = 1'b1; D = 1'b0; E = 1'b1;
    #2; A = 1'b0; B = 1'b0; C = 1'b1; D = 1'b1; E = 1'b0; 
    #2; A = 1'b0; B = 1'b0; C = 1'b1; D = 1'b1; E = 1'b1;
    #2; A = 1'b0; B = 1'b1; C = 1'b0; D = 1'b0; E = 1'b0; 
    #2; A = 1'b0; B = 1'b1; C = 1'b0; D = 1'b0; E = 1'b1;
    #2; A = 1'b0; B = 1'b1; C = 1'b0; D = 1'b1; E = 1'b0; 
    #2; A = 1'b0; B = 1'b1; C = 1'b0; D = 1'b1; E = 1'b1;
    #2; A = 1'b0; B = 1'b1; C = 1'b1; D = 1'b0; E = 1'b0; 
    #2; A = 1'b0; B = 1'b1; C = 1'b1; D = 1'b0; E = 1'b1;
    #2; A = 1'b0; B = 1'b1; C = 1'b1; D = 1'b1; E = 1'b0; 
    #2; A = 1'b0; B = 1'b1; C = 1'b1; D = 1'b1; E = 1'b1;

    #2; A = 1'b1; B = 1'b0; C = 1'b0; D = 1'b0; E = 1'b0; 
    #2; A = 1'b1; B = 1'b0; C = 1'b0; D = 1'b0; E = 1'b1;
    #2; A = 1'b1; B = 1'b0; C = 1'b0; D = 1'b1; E = 1'b0; 
    #2; A = 1'b1; B = 1'b0; C = 1'b0; D = 1'b1; E = 1'b1;
    #2; A = 1'b1; B = 1'b0; C = 1'b1; D = 1'b0; E = 1'b0; 
    #2; A = 1'b1; B = 1'b0; C = 1'b1; D = 1'b0; E = 1'b1;
    #2; A = 1'b1; B = 1'b0; C = 1'b1; D = 1'b1; E = 1'b0; 
    #2; A = 1'b1; B = 1'b0; C = 1'b1; D = 1'b1; E = 1'b1;
    #2; A = 1'b1; B = 1'b1; C = 1'b0; D = 1'b0; E = 1'b0; 
    #2; A = 1'b1; B = 1'b1; C = 1'b0; D = 1'b0; E = 1'b1;
    #2; A = 1'b1; B = 1'b1; C = 1'b0; D = 1'b1; E = 1'b0; 
    #2; A = 1'b1; B = 1'b1; C = 1'b0; D = 1'b1; E = 1'b1;
    #2; A = 1'b1; B = 1'b1; C = 1'b1; D = 1'b0; E = 1'b0; 
    #2; A = 1'b1; B = 1'b1; C = 1'b1; D = 1'b0; E = 1'b1;
    #2; A = 1'b1; B = 1'b1; C = 1'b1; D = 1'b1; E = 1'b0; 
    #2; A = 1'b1; B = 1'b1; C = 1'b1; D = 1'b1; E = 1'b1;
    #2;
    
    $finish;
end
    
endmodule

testbench.vcd
$date
	Sat Mar 27 14:46:56 2021
$end
$version
	Icarus Verilog
$end
$timescale
	1s
$end
$scope module testbench $end
$scope module meuModuloTeste $end
$var wire 1 ! a $end
$var wire 1 " b $end
$var wire 1 # c $end
$var wire 1 $ d $end
$var wire 1 % e $end
$var wire 1 & s1 $end
$var wire 1 ' s2 $end
$var wire 1 ( s3 $end
$var wire 1 ) s4 $end
$var wire 1 * s5 $end
$var wire 1 + s6 $end
$var wire 1 , s7 $end
$upscope $end
$upscope $end
$enddefinitions $end
#0
$dumpvars
1,
1+
0*
1)
1(
0'
1&
0%
0$
0#
0"
0!
$end
#2
0&
1'
0)
1%
#4
0%
1$
#6
1&
1)
0+
1%
#8
0&
0)
1+
0%
0$
1#
#10
1&
1)
0+
1%
#12
1&
1)
0%
1$
#14
0(
1*
1&
1%
#16
0&
0*
0)
1(
1+
0%
0$
0#
1"
#18
1&
0+
1)
1%
#20
1&
1)
0%
1$
#22
0(
1*
1)
1%
#24
0*
1(
1&
0%
0$
1#
#26
0(
1*
1)
1%
#28
1)
0%
1$
#30
0&
0)
0*
1(
0,
1%
#32
1(
1+
1,
0%
0$
0#
0"
1!
#34
1)
1&
0+
1%
#36
1)
0%
1$
#38
0(
1*
1%
#40
1(
0*
1&
0%
0$
1#
#42
0(
1*
1)
1%
#44
1&
0%
1$
#46
0&
0*
1(
0)
0,
1%
#48
1&
1)
1(
1,
0%
0$
0#
1"
#50
0(
1*
1%
#52
1&
1)
0%
1$
#54
0&
0)
0*
1(
0,
1%
#56
1&
1)
0(
1*
1,
0%
0$
1#
#58
0&
0)
0*
1(
0,
1%
#60
0)
0%
1$
#62
1&
1)
1*
1+
1%
